<?xml version="1.0" encoding="utf-8"?>
<xml>
  <Scripts>
    <Script>ASL-MAR</Script>
    <Price>24.62</Price>
  </Scripts>
  <Scripts>
    <Script>ASTL-MAR</Script>
    <Price>43.38</Price>
  </Scripts>
  <Scripts>
    <Script>AKBL-MAR</Script>
    <Price>21.27</Price>
  </Scripts>
  <Scripts>
    <Script>ATRL-MAR</Script>
    <Price>222.54</Price>
  </Scripts>
  <Scripts>
    <Script>AVN-MAR</Script>
    <Price>90.4</Price>
  </Scripts>
  <Scripts>
    <Script>BAHL-MAR</Script>
    <Price>65.83</Price>
  </Scripts>
  <Scripts>
    <Script>BAFL-MAR</Script>
    <Price>31.75</Price>
  </Scripts>
  <Scripts>
    <Script>BOP-MAR</Script>
    <Price>8.26</Price>
  </Scripts>
  <Scripts>
    <Script>BYCO-MAR</Script>
    <Price>11.03</Price>
  </Scripts>
  <Scripts>
    <Script>CEPB-MAR</Script>
    <Price>100</Price>
  </Scripts>
  <Scripts>
    <Script>CHCC-MAR</Script>
    <Price>166.24</Price>
  </Scripts>
  <Scripts>
    <Script>DGKC-MAR</Script>
    <Price>125.48</Price>
  </Scripts>
  <Scripts>
    <Script>ENGRO-MAR</Script>
    <Price>287.59</Price>
  </Scripts>
  <Scripts>
    <Script>EFERT-MAR</Script>
    <Price>62.71</Price>
  </Scripts>
  <Scripts>
    <Script>EPCL-MAR</Script>
    <Price>52.4</Price>
  </Scripts>
  <Scripts>
    <Script>FCCL-MAR</Script>
    <Price>23.07</Price>
  </Scripts>
  <Scripts>
    <Script>FFBL-MAR</Script>
    <Price>26.97</Price>
  </Scripts>
  <Scripts>
    <Script>FFC-MAR</Script>
    <Price>105</Price>
  </Scripts>
  <Scripts>
    <Script>FABL-MAR</Script>
    <Price>16.74</Price>
  </Scripts>
  <Scripts>
    <Script>GTYR-MAR</Script>
    <Price>89.95</Price>
  </Scripts>
  <Scripts>
    <Script>GHNI-MAR</Script>
    <Price>260.59</Price>
  </Scripts>
  <Scripts>
    <Script>GHNL-MAR</Script>
    <Price>104.73</Price>
  </Scripts>
  <Scripts>
    <Script>GGL-MAR</Script>
    <Price>21.96</Price>
  </Scripts>
  <Scripts>
    <Script>GATM-MAR</Script>
    <Price>46.1</Price>
  </Scripts>
  <Scripts>
    <Script>HBL-MAR</Script>
    <Price>121.38</Price>
  </Scripts>
  <Scripts>
    <Script>HASCOL-MAR</Script>
    <Price>10.5</Price>
  </Scripts>
  <Scripts>
    <Script>HUBC-MAR</Script>
    <Price>83.5</Price>
  </Scripts>
  <Scripts>
    <Script>HUMNL-MAR</Script>
    <Price>6.96</Price>
  </Scripts>
  <Scripts>
    <Script>INIL-MAR</Script>
    <Price>206.13</Price>
  </Scripts>
  <Scripts>
    <Script>ISL-MAR</Script>
    <Price>87.62</Price>
  </Scripts>
  <Scripts>
    <Script>KEL-MAR</Script>
    <Price>4.26</Price>
  </Scripts>
  <Scripts>
    <Script>KAPCO-MAR</Script>
    <Price>42.07</Price>
  </Scripts>
  <Scripts>
    <Script>LPL-MAR</Script>
    <Price>17.4</Price>
  </Scripts>
  <Scripts>
    <Script>LOTCHEM-MAR</Script>
    <Price>15.2</Price>
  </Scripts>
  <Scripts>
    <Script>LUCK-MAR</Script>
    <Price>842.16</Price>
  </Scripts>
  <Scripts>
    <Script>MLCF-MAR</Script>
    <Price>45.7</Price>
  </Scripts>
  <Scripts>
    <Script>MCB-MAR</Script>
    <Price>171.5</Price>
  </Scripts>
  <Scripts>
    <Script>MEBL-MAR</Script>
    <Price>112.26</Price>
  </Scripts>
  <Scripts>
    <Script>MUGHAL-MAR</Script>
    <Price>97.31</Price>
  </Scripts>
  <Scripts>
    <Script>NBP-MAR</Script>
    <Price>33.54</Price>
  </Scripts>
  <Scripts>
    <Script>NRL-MAR</Script>
    <Price>582.72</Price>
  </Scripts>
  <Scripts>
    <Script>NETSOL-MAR</Script>
    <Price>241.11</Price>
  </Scripts>
  <Scripts>
    <Script>NRSL-MAR</Script>
    <Price>11.85</Price>
  </Scripts>
  <Scripts>
    <Script>NCL-MAR</Script>
    <Price>47</Price>
  </Scripts>
  <Scripts>
    <Script>NML-MAR</Script>
    <Price>101.59</Price>
  </Scripts>
  <Scripts>
    <Script>OGDC-MAR</Script>
    <Price>100.05</Price>
  </Scripts>
  <Scripts>
    <Script>PAEL-MAR</Script>
    <Price>33.41</Price>
  </Scripts>
  <Scripts>
    <Script>PSMC-MAR</Script>
    <Price>264.59</Price>
  </Scripts>
  <Scripts>
    <Script>PIBTL-MAR</Script>
    <Price>10.8</Price>
  </Scripts>
  <Scripts>
    <Script>PPL-MAR</Script>
    <Price>86.21</Price>
  </Scripts>
  <Scripts>
    <Script>PRL-MAR</Script>
    <Price>25.33</Price>
  </Scripts>
  <Scripts>
    <Script>PSO-MAR</Script>
    <Price>233.57</Price>
  </Scripts>
  <Scripts>
    <Script>PTC-MAR</Script>
    <Price>8.44</Price>
  </Scripts>
  <Scripts>
    <Script>PIOC-MAR</Script>
    <Price>128.5</Price>
  </Scripts>
  <Scripts>
    <Script>POWER-MAR</Script>
    <Price>9.45</Price>
  </Scripts>
  <Scripts>
    <Script>SAZEW-MAR</Script>
    <Price>180.08</Price>
  </Scripts>
  <Scripts>
    <Script>STPL-MAR</Script>
    <Price>16.05</Price>
  </Scripts>
  <Scripts>
    <Script>SPL-MAR</Script>
    <Price>29.1</Price>
  </Scripts>
  <Scripts>
    <Script>SNGP-MAR</Script>
    <Price>39.28</Price>
  </Scripts>
  <Scripts>
    <Script>SSGC-MAR</Script>
    <Price>13.26</Price>
  </Scripts>
  <Scripts>
    <Script>TGL-MAR</Script>
    <Price>87.01</Price>
  </Scripts>
  <Scripts>
    <Script>SEARL-MAR</Script>
    <Price>252.01</Price>
  </Scripts>
  <Scripts>
    <Script>TREET-MAR</Script>
    <Price>27.71</Price>
  </Scripts>
  <Scripts>
    <Script>TRG-MAR</Script>
    <Price>141.21</Price>
  </Scripts>
  <Scripts>
    <Script>UBL-MARB</Script>
    <Price>120.49</Price>
  </Scripts>
  <Scripts>
    <Script>UNITY-MAR</Script>
    <Price>30.05</Price>
  </Scripts>
</xml>